[
    {
        "path":"/home/dmx/.config/background/img/splash",
        "name":"Color Explosion"
    },
    {
        "path":"/home/dmx/.config/background/img/pink_blue",
        "name":"Pink & Blue"
    },
    {
        "path":"/home/dmx/.config/background/img/evening",
        "name":"Evening Forrest"
    },
    {
        "path":"/home/dmx/.config/background/img/morning",
        "name":"Bright Morning"
    },
    {
        "path":"/home/dmx/.config/background/img/forrest_mountains",
        "name":"Forrests & Mountains"
    },
    {
        "path":"/home/dmx/.config/background/img/water",
        "name":"Water Mirror"
    },
    {
        "path":"/home/dmx/.config/background/img/night_mountains",
        "name":"Night Sky & Mountains"
    },
    {
        "path":"/home/dmx/.config/background/img/purple_wave",
        "name":"Purple Wave"
    },
    {
        "path":"/home/dmx/.config/background/img/dunes",
        "name":"Dunes"
    },
    {
        "path":"/home/dmx/.config/background/img/fire",
        "name":"Fire"
    },
    {
        "path":"/home/dmx/.config/background/img/pink_blue_gradient",
        "name":"Red & Blue Sediment"
    },
    {
        "path":"/home/dmx/.config/background/img/blue_flower",
        "name":"Blue Flower"
    },
    {
        "path":"/home/dmx/.config/background/img/gay2",
        "name":"Rainbow"
    }
]
